fovea/__init__.py
fovea/data/__init__.py
fovea/data/datadict.py
fovea/data/loaders.py
fovea/data/mini_imagenet.py
fovea/data/noisy_mnist.py
fovea/distributed/__init__.py
fovea/distributed/coalesce.py
fovea/distributed/launcher.py
fovea/distributed/manager.py
fovea/distributed/mpi.py
fovea/distributed/primitives.py
fovea/distributed/utils.py
fovea/learn/__init__.py
fovea/learn/layers.py
fovea/lightning/__init__.py
fovea/lightning/callbacks.py
fovea/lightning/checkpoint.py
fovea/lightning/core.py
fovea/lightning/loggers.py
fovea/lightning/multi_optimizer.py
fovea/lightning/records.py
fovea/lightning/trainer.py
fovea/utils/__init__.py
fovea/utils/_legacy_utils.py
fovea/utils/benchmark.py
fovea/utils/config_utils.py
fovea/utils/convert_utils.py
fovea/utils/file_utils.py
fovea/utils/functional_utils.py
fovea/utils/json_yaml_utils.py
fovea/utils/logging_utils.py
fovea/utils/metrics.py
fovea/utils/misc_utils.py
fovea/utils/np_utils.py
fovea/utils/print_utils.py
fovea/utils/termcolor.py
fovea/utils/timer.py
fovea/utils/torch_utils.py
fovea/utils/tracer.py
fovea/utils/tree_utils.py
fovea/utils/video_utils.py
omlet/__init__.py
omlet/distributed/__init__.py
omlet/distributed/mpi.py
omlet/distributed/torch_dist.py
omlet/learn/__init__.py
omlet/learn/layers.py
omlet/learn/transformer/__init__.py
omlet/learn/transformer/encoder.py
omlet/lightning/__init__.py
omlet/lightning/callbacks.py
omlet/lightning/checkpoint.py
omlet/lightning/core.py
omlet/lightning/loggers.py
omlet/lightning/records.py
omlet/lightning/trainer.py
omlet/utils/__init__.py
omlet/utils/config_utils.py
omlet/utils/file_utils.py
omlet/utils/json_yaml_utils.py
omlet/utils/logging_utils.py
omlet/utils/metrics.py
omlet/utils/misc_utils.py
omlet/utils/print_utils.py
omlet/utils/termcolor.py
omlet/utils/timer.py
omlet/utils/torch_utils.py
omlet/utils/tracer.py
omlet/utils/video_utils.py
fovea-0.1.1.dist-info/LICENSE
fovea-0.1.1.dist-info/METADATA
fovea-0.1.1.dist-info/WHEEL
fovea-0.1.1.dist-info/entry_points.txt
fovea-0.1.1.dist-info/top_level.txt
fovea-0.1.1.dist-info/RECORD
